odoo10_addon_l10n_br_purchase-10.0.1.0.0.99.dev21-py3.8-nspkg.pth
odoo/addons/l10n_br_purchase/README.rst
odoo/addons/l10n_br_purchase/__init__.py
odoo/addons/l10n_br_purchase/__manifest__.py
odoo/addons/l10n_br_purchase/data/l10n_br_purchase_data.xml
odoo/addons/l10n_br_purchase/demo/l10n_br_purchase_demo.xml
odoo/addons/l10n_br_purchase/i18n/pt_BR.po
odoo/addons/l10n_br_purchase/models/__init__.py
odoo/addons/l10n_br_purchase/models/procurement.py
odoo/addons/l10n_br_purchase/models/purchase.py
odoo/addons/l10n_br_purchase/models/purchase_line.py
odoo/addons/l10n_br_purchase/models/res_company.py
odoo/addons/l10n_br_purchase/readme/CONFIGURE.rst
odoo/addons/l10n_br_purchase/readme/CONTRIBUTORS.rst
odoo/addons/l10n_br_purchase/readme/CREDITS.rst
odoo/addons/l10n_br_purchase/readme/DESCRIPTION.rst
odoo/addons/l10n_br_purchase/readme/HISTORY.rst
odoo/addons/l10n_br_purchase/readme/INSTALL.rst
odoo/addons/l10n_br_purchase/readme/ROADMAP.rst
odoo/addons/l10n_br_purchase/readme/USAGE.rst
odoo/addons/l10n_br_purchase/security/ir.model.access.csv
odoo/addons/l10n_br_purchase/security/l10n_br_purchase_security.xml
odoo/addons/l10n_br_purchase/static/description/icon.png
odoo/addons/l10n_br_purchase/static/description/index.html
odoo/addons/l10n_br_purchase/tests/__init__.py
odoo/addons/l10n_br_purchase/tests/test_l10n_br_purchase.py
odoo/addons/l10n_br_purchase/views/purchase_view.xml
odoo/addons/l10n_br_purchase/views/res_company_view.xml
odoo/addons/l10n_br_purchase/wizard/__init__.py
odoo/addons/l10n_br_purchase/wizard/stock_invoice_onshipping.py
odoo10_addon_l10n_br_purchase-10.0.1.0.0.99.dev21.dist-info/METADATA
odoo10_addon_l10n_br_purchase-10.0.1.0.0.99.dev21.dist-info/WHEEL
odoo10_addon_l10n_br_purchase-10.0.1.0.0.99.dev21.dist-info/namespace_packages.txt
odoo10_addon_l10n_br_purchase-10.0.1.0.0.99.dev21.dist-info/top_level.txt
odoo10_addon_l10n_br_purchase-10.0.1.0.0.99.dev21.dist-info/RECORD
